pyseafuel/__init__.py
pyseafuel/_constants.py
pyseafuel/degasser.py
pyseafuel/desalinator.py
pyseafuel/dic.py
pyseafuel/electrolyzer.py
pyseafuel/reactor/__init__.py
pyseafuel/reactor/methane.py
pyseafuel/reactor/methanol.py
pyseafuel/system.py
pyseafuel-0.1.3.dist-info/METADATA
pyseafuel-0.1.3.dist-info/WHEEL
pyseafuel-0.1.3.dist-info/licenses/LICENSE
pyseafuel-0.1.3.dist-info/RECORD
